LICENSE
MANIFEST.in
README.md
setup.py
coreapidocs/__init__.py
coreapidocs/docs.py
coreapidocs.egg-info/PKG-INFO
coreapidocs.egg-info/SOURCES.txt
coreapidocs.egg-info/dependency_links.txt
coreapidocs.egg-info/requires.txt
coreapidocs.egg-info/top_level.txt
coreapidocs/static/less/styles.less
coreapidocs/templates/base.html
coreapidocs/templates/docs.html
tests/__init__.py
tests/test_basic.py