Metadata-Version: 1.1
Name: coreapidocs
Version: 0.0.2
Summary: Document APIs with CoreAPI.
Home-page: https://github.com/ekonstantinidis/coreapidocs
Author: Emmanouil Konstantinidis
Author-email: manos@iamemmanouil.com
License: BSD
Platform: UNKNOWN
Classifier: Development Status :: 5 - Production/Stable
Classifier: Environment :: Web Environment
Classifier: Intended Audience :: Developers
Classifier: License :: OSI Approved :: BSD License
Classifier: Operating System :: OS Independent
Classifier: Programming Language :: Python
Classifier: Programming Language :: Python :: 2.7
Classifier: Programming Language :: Python :: 3
Classifier: Programming Language :: Python :: 3.4
Classifier: Programming Language :: Python :: 3.5
